UniversalParser/__init__.py
UniversalParser/_collections.py
UniversalParser/_decorator.py
UniversalParser/_exception.py
UniversalParser/_ntype.py
UniversalParser/_parse.py
UniversalParser/_rely.py
UniversalParser/_tools.py
UniversalParser/manager.py
UniversalParser/struct.py
UniversalParser/html/__init__.py
UniversalParser/html/_ntype.py
UniversalParser/html/odict.py
UniversalParser/html/output.py
UniversalParser/html/templates.py
UniversalParser/micro/BaseTable.py
UniversalParser/micro/PowerPoint.py
UniversalParser/micro/Word.py
UniversalParser/micro/__init__.py
UniversalParser/micro/_ntype.py
UniversalParser/micro/UPExcel/ContentTypes.py
UniversalParser/micro/UPExcel/Sheet.py
UniversalParser/micro/UPExcel/WorkBook.py
UniversalParser/micro/UPExcel/__init__.py
UniversalParser/micro/UPExcel/_tools.py
UniversalParser/micro/UPExcel/constant.py
UniversalParser/xml/__init__.py
UniversalParser/xml/odict.py
UniversalParser/xml/unparser.py
UniversalParser-0.2.8.2.dist-info/LICENSE
UniversalParser-0.2.8.2.dist-info/METADATA
UniversalParser-0.2.8.2.dist-info/WHEEL
UniversalParser-0.2.8.2.dist-info/top_level.txt
UniversalParser-0.2.8.2.dist-info/RECORD
