Metadata-Version: 2.1
Name: UniversalParser
Version: 0.2.8.2
Summary: 一款通用的文本格式解析器，支持XML、JSON、YAML、HTML、XHTML、Word、Excel、PPT等文本格式的快速解析，在方法上具有高度一致性。
Home-page: https://gitee.com/jiyangj/universal-parser
Author: jiyang
Author-email: jiyangj@foxmail.com
License: UNKNOWN
Platform: UNKNOWN
Classifier: Programming Language :: Python :: 3
Classifier: License :: OSI Approved :: MIT License
Classifier: Operating System :: OS Independent
Requires-Python: >=3.5
License-File: LICENSE
